{
  "href": "https://naughtybounty.com/challenges/create",
  "brandTagline": "Adult-Challenge-Marketplace",
  "headlinePre": "Custom Content bestellen —",
  "headlineAccent": "ohne Chaos",
  "headlinePost": "",
  "badge": "Treuhand · Verifiziert",
  "cta": "Challenge erstellen",
  "urlLine": "naughtybounty.com",
  "bullets": [
    {
      "title": "Challenge erstellen",
      "description": "Budget, Thema & Bedingungen festlegen"
    },
    {
      "title": "Creator wählen",
      "description": "Bewerbungen vergleichen — du entscheidest"
    },
    {
      "title": "Sicher bezahlen",
      "description": "Geld in Treuhand bis zur Lieferung"
    }
  ]
}
